stat_df/__init__.py
stat_df/statistics.py
stat_df-0.1.5.dist-info/licenses/LICENSE.txt
stat_df-0.1.5.dist-info/METADATA
stat_df-0.1.5.dist-info/WHEEL
stat_df-0.1.5.dist-info/top_level.txt
stat_df-0.1.5.dist-info/RECORD
