Metadata-Version: 2.4
Name: stat_df
Version: 0.1.5
Summary: A library for advanced DataFrame statistics analysis.
Author-email: Andrew Romanov <romanoffnv@gmail.com>
License: MIT
Requires-Python: >=3.6
License-File: LICENSE.txt
Requires-Dist: pandas
Requires-Dist: numpy
Requires-Dist: matplotlib
Requires-Dist: seaborn
Dynamic: license-file
